[
  {
    "name": "Berserker's Greaves",
    "image": "./img/Berserker_s_Greaves.png"
  },
  {
    "name": "Boots",
    "image": "./img/Boots.png"
  },
  {
    "name": "Boots of Swiftness",
    "image": "./img/Boots_of_Swiftness.png"
  },
  {
    "name": "Ionian Boots of Lucidity",
    "image": "./img/Ionian_Boots_of_Lucidity.png"
  },
  {
    "name": "Mercury's Treads",
    "image": "./img/Mercury_s_Treads.png"
  },
  {
    "name": "Mobility Boots",
    "image": "./img/Mobility_Boots.png"
  },
  {
    "name": "Plated Steelcaps",
    "image": "./img/Plated_Steelcaps.png"
  },
  {
    "name": "Sorcerer's Shoes",
    "image": "./img/Sorcerer_s_Shoes.png"
  }
]